luscious_dl/__init__.py
luscious_dl/album.py
luscious_dl/command_line.py
luscious_dl/downloader.py
luscious_dl/exceptions.py
luscious_dl/logger.py
luscious_dl/menu.py
luscious_dl/parser.py
luscious_dl/querys.py
luscious_dl/start.py
luscious_dl/user.py
luscious_dl/utils.py
luscious_downloader-4.11.1.dist-info/LICENSE
luscious_downloader-4.11.1.dist-info/METADATA
luscious_downloader-4.11.1.dist-info/WHEEL
luscious_downloader-4.11.1.dist-info/entry_points.txt
luscious_downloader-4.11.1.dist-info/top_level.txt
luscious_downloader-4.11.1.dist-info/RECORD
