Metadata-Version: 2.1
Name: luscious-downloader
Version: 4.11.1
Summary: CLI tool for downloading albums from Luscious
Home-page: https://github.com/Lucas8x/luscious-downloader
Author: Lucas8x
Author-email: 
License: MIT
Project-URL: Source, https://github.com/Lucas8x/luscious-downloader
Project-URL: Tracker, https://github.com/Lucas8x/luscious-downloader/issues
Keywords: luscious,album,downloader
Classifier: Programming Language :: Python :: 3
Classifier: Programming Language :: Python :: 3.6
Classifier: Programming Language :: Python :: 3.7
Classifier: Programming Language :: Python :: 3.8
Classifier: Programming Language :: Python :: 3.9
Classifier: Programming Language :: Python :: 3.10
Classifier: Programming Language :: Python :: 3.11
Classifier: Environment :: Console
Classifier: Intended Audience :: End Users/Desktop
Classifier: License :: OSI Approved :: MIT License
Classifier: Natural Language :: English
Classifier: Topic :: Terminals
Classifier: Topic :: Utilities
Requires-Python: >=3.9
License-File: LICENSE
Requires-Dist: colorlog (>=5)
Requires-Dist: requests (>=2.25)
Requires-Dist: tabulate (>=0.8.7)
Provides-Extra: pdf
Requires-Dist: Pillow (>=8.2.0) ; extra == 'pdf'
Requires-Dist: tqdm ; extra == 'pdf'
